Claridata/__init__.py
Claridata/claridata.py
Claridata/modules.py
claridata-0.1.0.dist-info/METADATA
claridata-0.1.0.dist-info/WHEEL
claridata-0.1.0.dist-info/top_level.txt
claridata-0.1.0.dist-info/RECORD
